RAM/RAM.v
module RAM # (
    parameter INIT = "MEMINIT.txt"
) (
// INPUTS
input wire reset,
input wire clock,
input wire read,
input wire write,
input wire [3:0] WriteAddr,
input wire [3:0] ReadAddr,
input wire [7:0] WriteData,
// Outputs
output reg [7:0] ReadData,
output reg ReadReady,
output reg WriteReady
);

reg [7:0] mem [0:15];

always @ (posedge clock or posedge reset) begin
    if (reset) begin
        WriteReady = 0;
        $readmemh(INIT, mem);
    end else begin
        if (write) begin
            mem[WriteAddr] <= WriteData;
            WriteReady = 0;
        end else begin
            WriteReady = 1;
        end
        if (read) begin
            ReadData <= mem[ReadAddr];
            ReadReady = 0;
        end else begin
            ReadReady = 1;
        end
    end
end
endmodule

RAM/TEST_tb.v
`timescale 1ns/10ps
module test();
reg clk = 0;
reg reset = 0;

always begin
    #41.667

    clk = ~clk;
end

initial begin
    reset = 1;
    #250
    reset = 0;
end

initial begin
    $dumpfile("TEST_tb.vcd");
    $dumpvars(0, test);
    #22000

    $display("Finished");
    $finish;
end

// always @ (posedge WriteReady) begin
//
//end
always @ (posedge clk) begin
    write <= 0;
    read <= 0;
    if (counter) begin
        if (WriteReady) begin
            WriteAddr <= WriteAddr + 1;
            WriteData <= $urandom_range(255,0);
            write <= 1;
        end
        if (ReadReady) begin
            ReadAddr <= ReadAddr + 1;
            Data <= ReadData;
            read <= 1;
        end
    end
    counter = counter + 1;
end

RAM RAM(
    .clock(clk),
    .WriteReady(WriteReady),
    .ReadReady(ReadReady),
    .write(write),
    .read(read),
    .WriteAddr(WriteAddr),
    .ReadAddr(ReadAddr),
    .WriteData(WriteData),
    .ReadData(ReadData)
);
reg [0:0] write;
reg [0:0] read;

reg [7:0] Data;

reg counter = 1'b0;

reg [3:0] WriteAddr = 4'b0000;
reg [3:0] ReadAddr = 4'b0000;
reg [7:0] WriteData = 7'b0000000;
wire [7:0] ReadData = 7'b0000000;
wire WriteReady;
wire ReadReady;

endmodule

RAM/TEST_tb.vcd
$date
	Fri Feb 17 11:03:39 2023
$end
$version
	Icarus Verilog
$end
$timescale
	1ps
$end
$scope module test $end
$var wire 8 ! ReadData [7:0] $end
$var wire 1 " WriteReady $end
$var wire 1 # ReadReady $end
$var reg 8 $ Data [7:0] $end
$var reg 4 % ReadAddr [3:0] $end
$var reg 4 & WriteAddr [3:0] $end
$var reg 8 ' WriteData [7:0] $end
$var reg 1 ( clk $end
$var reg 1 ) counter $end
$var reg 1 * read $end
$var reg 1 + reset $end
$var reg 1 , write $end
$scope module RAM $end
$var wire 4 - ReadAddr [3:0] $end
$var wire 4 . WriteAddr [3:0] $end
$var wire 8 / WriteData [7:0] $end
$var wire 1 ( clock $end
$var wire 1 * read $end
$var wire 1 0 reset $end
$var wire 1 , write $end
$var reg 8 1 ReadData [7:0] $end
$var reg 1 # ReadReady $end
$var reg 1 " WriteReady $end
$upscope $end
$upscope $end
$enddefinitions $end
#0
$dumpvars
bx 1
z0
b0 /
b0 .
b0 -
x,
1+
x*
0)
0(
b0 '
b0 &
b0 %
bx $
x#
x"
bx !
$end
#41670
0*
0,
1#
1"
1)
1(
#83340
0(
#125010
1*
b1 %
b1 -
1,
b10010010 '
b10010010 /
b1 &
b1 .
0)
1(
#166680
0(
#200000
0+
#208350
0*
0,
0#
0"
1)
1(
#250020
0(
#291690
1#
1"
0)
1(
#333360
0(
#375030
1)
1(
#416700
0(
#458370
1*
b10 %
b10 -
1,
b1000000 '
b1000000 /
b10 &
b10 .
0)
1(
#500040
0(
#541710
0*
0,
0#
0"
1)
1(
#583380
0(
#625050
1#
1"
0)
1(
#666720
0(
#708390
1)
1(
#750060
0(
#791730
1*
b11 %
b11 -
1,
b100 '
b100 /
b11 &
b11 .
0)
1(
#833400
0(
#875070
0*
0,
0#
0"
1)
1(
#916740
0(
#958410
1#
1"
0)
1(
#1000080
0(
#1041750
1)
1(
#1083420
0(
#1125090
1*
b100 %
b100 -
1,
b110001 '
b110001 /
b100 &
b100 .
0)
1(
#1166760
0(
#1208430
0*
0,
0#
0"
1)
1(
#1250100
0(
#1291770
1#
1"
0)
1(
#1333440
0(
#1375110
1)
1(
#1416780
0(
#1458450
1*
b101 %
b101 -
1,
b10000110 '
b10000110 /
b101 &
b101 .
0)
1(
#1500120
0(
#1541790
0*
0,
0#
0"
1)
1(
#1583460
0(
#1625130
1#
1"
0)
1(
#1666800
0(
#1708470
1)
1(
#1750140
0(
#1791810
1*
b110 %
b110 -
1,
b11000110 '
b11000110 /
b110 &
b110 .
0)
1(
#1833480
0(
#1875150
0*
0,
0#
0"
1)
1(
#1916820
0(
#1958490
1#
1"
0)
1(
#2000160
0(
#2041830
1)
1(
#2083500
0(
#2125170
1*
b111 %
b111 -
1,
b110010 '
b110010 /
b111 &
b111 .
0)
1(
#2166840
0(
#2208510
0*
0,
0#
0"
1)
1(
#2250180
0(
#2291850
1#
1"
0)
1(
#2333520
0(
#2375190
1)
1(
#2416860
0(
#2458530
1*
b1000 %
b1000 -
1,
b1001 '
b1001 /
b1000 &
b1000 .
0)
1(
#2500200
0(
#2541870
0*
0,
0#
0"
1)
1(
#2583540
0(
#2625210
1#
1"
0)
1(
#2666880
0(
#2708550
1)
1(
#2750220
0(
#2791890
1*
b1001 %
b1001 -
1,
b10000000 '
b10000000 /
b1001 &
b1001 .
0)
1(
#2833560
0(
#2875230
0*
0,
0#
0"
1)
1(
#2916900
0(
#2958570
1#
1"
0)
1(
#3000240
0(
#3041910
1)
1(
#3083580
0(
#3125250
1*
b1010 %
b1010 -
1,
b10000110 '
b10000110 /
b1010 &
b1010 .
0)
1(
#3166920
0(
#3208590
0*
0,
0#
0"
1)
1(
#3250260
0(
#3291930
1#
1"
0)
1(
#3333600
0(
#3375270
1)
1(
#3416940
0(
#3458610
1*
b1011 %
b1011 -
1,
b10111011 '
b10111011 /
b1011 &
b1011 .
0)
1(
#3500280
0(
#3541950
0*
0,
0#
0"
1)
1(
#3583620
0(
#3625290
1#
1"
0)
1(
#3666960
0(
#3708630
1)
1(
#3750300
0(
#3791970
1*
b1100 %
b1100 -
1,
b10011110 '
b10011110 /
b1100 &
b1100 .
0)
1(
#3833640
0(
#3875310
0*
0,
0#
0"
1)
1(
#3916980
0(
#3958650
1#
1"
0)
1(
#4000320
0(
#4041990
1)
1(
#4083660
0(
#4125330
1*
b1101 %
b1101 -
1,
b11110110 '
b11110110 /
b1101 &
b1101 .
0)
1(
#4167000
0(
#4208670
0*
0,
0#
0"
1)
1(
#4250340
0(
#4292010
1#
1"
0)
1(
#4333680
0(
#4375350
1)
1(
#4417020
0(
#4458690
1*
b1110 %
b1110 -
1,
b11000110 '
b11000110 /
b1110 &
b1110 .
0)
1(
#4500360
0(
#4542030
0*
0,
0#
0"
1)
1(
#4583700
0(
#4625370
1#
1"
0)
1(
#4667040
0(
#4708710
1)
1(
#4750380
0(
#4792050
1*
b1111 %
b1111 -
1,
b11111100 '
b11111100 /
b1111 &
b1111 .
0)
1(
#4833720
0(
#4875390
0*
0,
0#
0"
1)
1(
#4917060
0(
#4958730
1#
1"
0)
1(
#5000400
0(
#5042070
1)
1(
#5083740
0(
#5125410
1*
b0 %
b0 -
1,
b1100011 '
b1100011 /
b0 &
b0 .
0)
1(
#5167080
0(
#5208750
0*
0,
0#
0"
1)
1(
#5250420
0(
#5292090
1#
1"
0)
1(
#5333760
0(
#5375430
1)
1(
#5417100
0(
#5458770
1*
b1 %
b1 -
1,
b1100010 '
b1100010 /
b1 &
b1 .
0)
1(
#5500440
0(
#5542110
bx00x00x0 !
b10010010 1
0*
0,
0#
0"
1)
1(
#5583780
0(
#5625450
1#
1"
0)
1(
#5667120
0(
#5708790
1)
1(
#5750460
0(
#5792130
1*
bx00x00x0 $
b10 %
b10 -
1,
b1010101 '
b1010101 /
b10 &
b10 .
0)
1(
#5833800
0(
#5875470
b0x000000 !
b1000000 1
0*
0,
0#
0"
1)
1(
#5917140
0(
#5958810
1#
1"
0)
1(
#6000480
0(
#6042150
1)
1(
#6083820
0(
#6125490
1*
b0x000000 $
b11 %
b11 -
1,
b11110010 '
b11110010 /
b11 &
b11 .
0)
1(
#6167160
0(
#6208830
b0x00 !
b100 1
0*
0,
0#
0"
1)
1(
#6250500
0(
#6292170
1#
1"
0)
1(
#6333840
0(
#6375510
1)
1(
#6417180
0(
#6458850
1*
b0x00 $
b100 %
b100 -
1,
b111011 '
b111011 /
b100 &
b100 .
0)
1(
#6500520
0(
#6542190
b0xx000x !
b110001 1
0*
0,
0#
0"
1)
1(
#6583860
0(
#6625530
1#
1"
0)
1(
#6667200
0(
#6708870
1)
1(
#6750540
0(
#6792210
1*
b0xx000x $
b101 %
b101 -
1,
b1001 '
b1001 /
b101 &
b101 .
0)
1(
#6833880
0(
#6875550
bx0000xx0 !
b10000110 1
0*
0,
0#
0"
1)
1(
#6917220
0(
#6958890
1#
1"
0)
1(
#7000560
0(
#7042230
1)
1(
#7083900
0(
#7125570
1*
bx0000xx0 $
b110 %
b110 -
1,
b11000111 '
b11000111 /
b110 &
b110 .
0)
1(
#7167240
0(
#7208910
bx000xx0 !
b11000110 1
0*
0,
0#
0"
1)
1(
#7250580
0(
#7292250
1#
1"
0)
1(
#7333920
0(
#7375590
1)
1(
#7417260
0(
#7458930
1*
bx000xx0 $
b111 %
b111 -
1,
b11111001 '
b11111001 /
b111 &
b111 .
0)
1(
#7500600
0(
#7542270
b0xx00x0 !
b110010 1
0*
0,
0#
0"
1)
1(
#7583940
0(
#7625610
1#
1"
0)
1(
#7667280
0(
#7708950
1)
1(
#7750620
0(
#7792290
1*
b0xx00x0 $
b1000 %
b1000 -
1,
b1100111 '
b1100111 /
b1000 &
b1000 .
0)
1(
#7833960
0(
#7875630
b0x00x !
b1001 1
0*
0,
0#
0"
1)
1(
#7917300
0(
#7958970
1#
1"
0)
1(
#8000640
0(
#8042310
1)
1(
#8083980
0(
#8125650
1*
b0x00x $
b1001 %
b1001 -
1,
b1110100 '
b1110100 /
b1001 &
b1001 .
0)
1(
#8167320
0(
#8208990
bx0000000 !
b10000000 1
0*
0,
0#
0"
1)
1(
#8250660
0(
#8292330
1#
1"
0)
1(
#8334000
0(
#8375670
1)
1(
#8417340
0(
#8459010
1*
bx0000000 $
b1010 %
b1010 -
1,
b1100010 '
b1100010 /
b1010 &
b1010 .
0)
1(
#8500680
0(
#8542350
bx0000xx0 !
b10000110 1
0*
0,
0#
0"
1)
1(
#8584020
0(
#8625690
1#
1"
0)
1(
#8667360
0(
#8709030
1)
1(
#8750700
0(
#8792370
1*
bx0000xx0 $
b1011 %
b1011 -
1,
b10101110 '
b10101110 /
b1011 &
b1011 .
0)
1(
#8834040
0(
#8875710
bx0xxx0xx !
b10111011 1
0*
0,
0#
0"
1)
1(
#8917380
0(
#8959050
1#
1"
0)
1(
#9000720
0(
#9042390
1)
1(
#9084060
0(
#9125730
1*
bx0xxx0xx $
b1100 %
b1100 -
1,
b1011110 '
b1011110 /
b1100 &
b1100 .
0)
1(
#9167400
0(
#9209070
bx00xxxx0 !
b10011110 1
0*
0,
0#
0"
1)
1(
#9250740
0(
#9292410
1#
1"
0)
1(
#9334080
0(
#9375750
1)
1(
#9417420
0(
#9459090
1*
bx00xxxx0 $
b1101 %
b1101 -
1,
b10110 '
b10110 /
b1101 &
b1101 .
0)
1(
#9500760
0(
#9542430
bx0xx0 !
b11110110 1
0*
0,
0#
0"
1)
1(
#9584100
0(
#9625770
1#
1"
0)
1(
#9667440
0(
#9709110
1)
1(
#9750780
0(
#9792450
1*
bx0xx0 $
b1110 %
b1110 -
1,
b110010 '
b110010 /
b1110 &
b1110 .
0)
1(
#9834120
0(
#9875790
bx000xx0 !
b11000110 1
0*
0,
0#
0"
1)
1(
#9917460
0(
#9959130
1#
1"
0)
1(
#10000800
0(
#10042470
1)
1(
#10084140
0(
#10125810
1*
bx000xx0 $
b1111 %
b1111 -
1,
b110001 '
b110001 /
b1111 &
b1111 .
0)
1(
#10167480
0(
#10209150
bx00 !
b11111100 1
0*
0,
0#
0"
1)
1(
#10250820
0(
#10292490
1#
1"
0)
1(
#10334160
0(
#10375830
1)
1(
#10417500
0(
#10459170
1*
bx00 $
b0 %
b0 -
1,
b10000101 '
b10000101 /
b0 &
b0 .
0)
1(
#10500840
0(
#10542510
b0xx000xx !
b1100011 1
0*
0,
0#
0"
1)
1(
#10584180
0(
#10625850
1#
1"
0)
1(
#10667520
0(
#10709190
1)
1(
#10750860
0(
#10792530
1*
b0xx000xx $
b1 %
b1 -
1,
b1000000 '
b1000000 /
b1 &
b1 .
0)
1(
#10834200
0(
#10875870
b0xx000x0 !
b1100010 1
0*
0,
0#
0"
1)
1(
#10917540
0(
#10959210
1#
1"
0)
1(
#11000880
0(
#11042550
1)
1(
#11084220
0(
#11125890
1*
b0xx000x0 $
b10 %
b10 -
1,
b10010000 '
b10010000 /
b10 &
b10 .
0)
1(
#11167560
0(
#11209230
b0x0x0x0x !
b1010101 1
0*
0,
0#
0"
1)
1(
#11250900
0(
#11292570
1#
1"
0)
1(
#11334240
0(
#11375910
1)
1(
#11417580
0(
#11459250
1*
b0x0x0x0x $
b11 %
b11 -
1,
b11010101 '
b11010101 /
b11 &
b11 .
0)
1(
#11500920
0(
#11542590
bx00x0 !
b11110010 1
0*
0,
0#
0"
1)
1(
#11584260
0(
#11625930
1#
1"
0)
1(
#11667600
0(
#11709270
1)
1(
#11750940
0(
#11792610
1*
bx00x0 $
b100 %
b100 -
1,
b1001110 '
b1001110 /
b100 &
b100 .
0)
1(
#11834280
0(
#11875950
b0xxx0xx !
b111011 1
0*
0,
0#
0"
1)
1(
#11917620
0(
#11959290
1#
1"
0)
1(
#12000960
0(
#12042630
1)
1(
#12084300
0(
#12125970
1*
b0xxx0xx $
b101 %
b101 -
1,
b1001011 '
b1001011 /
b101 &
b101 .
0)
1(
#12167640
0(
#12209310
b0x00x !
b1001 1
0*
0,
0#
0"
1)
1(
#12250980
0(
#12292650
1#
1"
0)
1(
#12334320
0(
#12375990
1)
1(
#12417660
0(
#12459330
1*
b0x00x $
b110 %
b110 -
1,
b1001 '
b1001 /
b110 &
b110 .
0)
1(
#12501000
0(
#12542670
bx000xxx !
b11000111 1
0*
0,
0#
0"
1)
1(
#12584340
0(
#12626010
1#
1"
0)
1(
#12667680
0(
#12709350
1)
1(
#12751020
0(
#12792690
1*
bx000xxx $
b111 %
b111 -
1,
b110 '
b110 /
b111 &
b111 .
0)
1(
#12834360
0(
#12876030
bx00x !
b11111001 1
0*
0,
0#
0"
1)
1(
#12917700
0(
#12959370
1#
1"
0)
1(
#13001040
0(
#13042710
1)
1(
#13084380
0(
#13126050
1*
bx00x $
b1000 %
b1000 -
1,
b101001 '
b101001 /
b1000 &
b1000 .
0)
1(
#13167720
0(
#13209390
b0xx00xxx !
b1100111 1
0*
0,
0#
0"
1)
1(
#13251060
0(
#13292730
1#
1"
0)
1(
#13334400
0(
#13376070
1)
1(
#13417740
0(
#13459410
1*
b0xx00xxx $
b1001 %
b1001 -
1,
b10110101 '
b10110101 /
b1001 &
b1001 .
0)
1(
#13501080
0(
#13542750
b0xxx0x00 !
b1110100 1
0*
0,
0#
0"
1)
1(
#13584420
0(
#13626090
1#
1"
0)
1(
#13667760
0(
#13709430
1)
1(
#13751100
0(
#13792770
1*
b0xxx0x00 $
b1010 %
b1010 -
1,
b1101010 '
b1101010 /
b1010 &
b1010 .
0)
1(
#13834440
0(
#13876110
b0xx000x0 !
b1100010 1
0*
0,
0#
0"
1)
1(
#13917780
0(
#13959450
1#
1"
0)
1(
#14001120
0(
#14042790
1)
1(
#14084460
0(
#14126130
1*
b0xx000x0 $
b1011 %
b1011 -
1,
b1 '
b1 /
b1011 &
b1011 .
0)
1(
#14167800
0(
#14209470
bx0x0xxx0 !
b10101110 1
0*
0,
0#
0"
1)
1(
#14251140
0(
#14292810
1#
1"
0)
1(
#14334480
0(
#14376150
1)
1(
#14417820
0(
#14459490
1*
bx0x0xxx0 $
b1100 %
b1100 -
1,
b1010111 '
b1010111 /
b1100 &
b1100 .
0)
1(
#14501160
0(
#14542830
b0x0xxxx0 !
b1011110 1
0*
0,
0#
0"
1)
1(
#14584500
0(
#14626170
1#
1"
0)
1(
#14667840
0(
#14709510
1)
1(
#14751180
0(
#14792850
1*
b0x0xxxx0 $
b1101 %
b1101 -
1,
b10001110 '
b10001110 /
b1101 &
b1101 .
0)
1(
#14834520
0(
#14876190
b0x0xx0 !
b10110 1
0*
0,
0#
0"
1)
1(
#14917860
0(
#14959530
1#
1"
0)
1(
#15001200
0(
#15042870
1)
1(
#15084540
0(
#15126210
1*
b0x0xx0 $
b1110 %
b1110 -
1,
b1100111 '
b1100111 /
b1110 &
b1110 .
0)
1(
#15167880
0(
#15209550
b0xx00x0 !
b110010 1
0*
0,
0#
0"
1)
1(
#15251220
0(
#15292890
1#
1"
0)
1(
#15334560
0(
#15376230
1)
1(
#15417900
0(
#15459570
1*
b0xx00x0 $
b1111 %
b1111 -
1,
b10010001 '
b10010001 /
b1111 &
b1111 .
0)
1(
#15501240
0(
#15542910
b0xx000x !
b110001 1
0*
0,
0#
0"
1)
1(
#15584580
0(
#15626250
1#
1"
0)
1(
#15667920
0(
#15709590
1)
1(
#15751260
0(
#15792930
1*
b0xx000x $
b0 %
b0 -
1,
b10000101 '
b10000101 /
b0 &
b0 .
0)
1(
#15834600
0(
#15876270
bx0000x0x !
b10000101 1
0*
0,
0#
0"
1)
1(
#15917940
0(
#15959610
1#
1"
0)
1(
#16001280
0(
#16042950
1)
1(
#16084620
0(
#16126290
1*
bx0000x0x $
b1 %
b1 -
1,
b1100101 '
b1100101 /
b1 &
b1 .
0)
1(
#16167960
0(
#16209630
b0x000000 !
b1000000 1
0*
0,
0#
0"
1)
1(
#16251300
0(
#16292970
1#
1"
0)
1(
#16334640
0(
#16376310
1)
1(
#16417980
0(
#16459650
1*
b0x000000 $
b10 %
b10 -
1,
b11110 '
b11110 /
b10 &
b10 .
0)
1(
#16501320
0(
#16542990
bx00x0000 !
b10010000 1
0*
0,
0#
0"
1)
1(
#16584660
0(
#16626330
1#
1"
0)
1(
#16668000
0(
#16709670
1)
1(
#16751340
0(
#16793010
1*
bx00x0000 $
b11 %
b11 -
1,
b11111001 '
b11111001 /
b11 &
b11 .
0)
1(
#16834680
0(
#16876350
bx0x0x0x !
b11010101 1
0*
0,
0#
0"
1)
1(
#16918020
0(
#16959690
1#
1"
0)
1(
#17001360
0(
#17043030
1)
1(
#17084700
0(
#17126370
1*
bx0x0x0x $
b100 %
b100 -
1,
b11000101 '
b11000101 /
b100 &
b100 .
0)
1(
#17168040
0(
#17209710
b0x00xxx0 !
b1001110 1
0*
0,
0#
0"
1)
1(
#17251380
0(
#17293050
1#
1"
0)
1(
#17334720
0(
#17376390
1)
1(
#17418060
0(
#17459730
1*
b0x00xxx0 $
b101 %
b101 -
1,
b10100000 '
b10100000 /
b101 &
b101 .
0)
1(
#17501400
0(
#17543070
b0x00x0xx !
b1001011 1
0*
0,
0#
0"
1)
1(
#17584740
0(
#17626410
1#
1"
0)
1(
#17668080
0(
#17709750
1)
1(
#17751420
0(
#17793090
1*
b0x00x0xx $
b110 %
b110 -
1,
b1101100 '
b1101100 /
b110 &
b110 .
0)
1(
#17834760
0(
#17876430
b0x00x !
b1001 1
0*
0,
0#
0"
1)
1(
#17918100
0(
#17959770
1#
1"
0)
1(
#18001440
0(
#18043110
1)
1(
#18084780
0(
#18126450
1*
b0x00x $
b111 %
b111 -
1,
b10111100 '
b10111100 /
b111 &
b111 .
0)
1(
#18168120
0(
#18209790
b0xx0 !
b110 1
0*
0,
0#
0"
1)
1(
#18251460
0(
#18293130
1#
1"
0)
1(
#18334800
0(
#18376470
1)
1(
#18418140
0(
#18459810
1*
b0xx0 $
b1000 %
b1000 -
1,
b1000100 '
b1000100 /
b1000 &
b1000 .
0)
1(
#18501480
0(
#18543150
b0x0x00x !
b101001 1
0*
0,
0#
0"
1)
1(
#18584820
0(
#18626490
1#
1"
0)
1(
#18668160
0(
#18709830
1)
1(
#18751500
0(
#18793170
1*
b0x0x00x $
b1001 %
b1001 -
1,
b11110101 '
b11110101 /
b1001 &
b1001 .
0)
1(
#18834840
0(
#18876510
bx0xx0x0x !
b10110101 1
0*
0,
0#
0"
1)
1(
#18918180
0(
#18959850
1#
1"
0)
1(
#19001520
0(
#19043190
1)
1(
#19084860
0(
#19126530
1*
bx0xx0x0x $
b1010 %
b1010 -
1,
b11011011 '
b11011011 /
b1010 &
b1010 .
0)
1(
#19168200
0(
#19209870
b0xx0x0x0 !
b1101010 1
0*
0,
0#
0"
1)
1(
#19251540
0(
#19293210
1#
1"
0)
1(
#19334880
0(
#19376550
1)
1(
#19418220
0(
#19459890
1*
b0xx0x0x0 $
b1011 %
b1011 -
1,
b11100011 '
b11100011 /
b1011 &
b1011 .
0)
1(
#19501560
0(
#19543230
b0x !
b1 1
0*
0,
0#
0"
1)
1(
#19584900
0(
#19626570
1#
1"
0)
1(
#19668240
0(
#19709910
1)
1(
#19751580
0(
#19793250
1*
b0x $
b1100 %
b1100 -
1,
b11010111 '
b11010111 /
b1100 &
b1100 .
0)
1(
#19834920
0(
#19876590
b0x0x0xxx !
b1010111 1
0*
0,
0#
0"
1)
1(
#19918260
0(
#19959930
1#
1"
0)
1(
#20001600
0(
#20043270
1)
1(
#20084940
0(
#20126610
1*
b0x0x0xxx $
b1101 %
b1101 -
1,
b1011110 '
b1011110 /
b1101 &
b1101 .
0)
1(
#20168280
0(
#20209950
bx000xxx0 !
b10001110 1
0*
0,
0#
0"
1)
1(
#20251620
0(
#20293290
1#
1"
0)
1(
#20334960
0(
#20376630
1)
1(
#20418300
0(
#20459970
1*
bx000xxx0 $
b1110 %
b1110 -
1,
b10010101 '
b10010101 /
b1110 &
b1110 .
0)
1(
#20501640
0(
#20543310
b0xx00xxx !
b1100111 1
0*
0,
0#
0"
1)
1(
#20584980
0(
#20626650
1#
1"
0)
1(
#20668320
0(
#20709990
1)
1(
#20751660
0(
#20793330
1*
b0xx00xxx $
b1111 %
b1111 -
1,
b101 '
b101 /
b1111 &
b1111 .
0)
1(
#20835000
0(
#20876670
bx00x000x !
b10010001 1
0*
0,
0#
0"
1)
1(
#20918340
0(
#20960010
1#
1"
0)
1(
#21001680
0(
#21043350
1)
1(
#21085020
0(
#21126690
1*
bx00x000x $
b0 %
b0 -
1,
b111000 '
b111000 /
b0 &
b0 .
0)
1(
#21168360
0(
#21210030
bx0000x0x !
b10000101 1
0*
0,
0#
0"
1)
1(
#21251700
0(
#21293370
1#
1"
0)
1(
#21335040
0(
#21376710
1)
1(
#21418380
0(
#21460050
1*
bx0000x0x $
b1 %
b1 -
1,
b11000010 '
b11000010 /
b1 &
b1 .
0)
1(
#21501720
0(
#21543390
b0xx00x0x !
b1100101 1
0*
0,
0#
0"
1)
1(
#21585060
0(
#21626730
1#
1"
0)
1(
#21668400
0(
#21710070
1)
1(
#21751740
0(
#21793410
1*
b0xx00x0x $
b10 %
b10 -
1,
b10100111 '
b10100111 /
b10 &
b10 .
0)
1(
#21835080
0(
#21876750
b0xxxx0 !
b11110 1
0*
0,
0#
0"
1)
1(
#21918420
0(
#21960090
1#
1"
0)
1(
