RAM/RAM.v
module RAM # (
    parameter INIT = "MEMINIT.txt"
) (
// INPUTS
input wire reset,
input wire clock,
input wire read,
input wire write,
input wire [3:0] WriteAddr,
input wire [3:0] ReadAddr,
input wire [7:0] WriteData,
// Outputs
output reg [7:0] ReadData,
output reg ReadReady,
output reg WriteReady
);

reg [7:0] mem [0:15];

always @ (posedge clock or posedge reset) begin
    if (reset) begin
        ReadReady = 0;
        WriteReady = 0;
        $readmemh(INIT, mem);
    end else begin
        if (read) begin
            ReadData <= mem[ReadAddr];
            ReadReady = 0;
        end else begin
            ReadReady = 1;
        end        
        if (write) begin
            mem[WriteAddr] <= WriteData;
            WriteReady = 0;
        end else begin
            WriteReady = 1;
        end
    end
end
endmodule

RAM/Clock.v
module Clock # (
	parameter COUNTERSIZE = 24,
	parameter COUNTERLIMIT = 6000000-1
) (
// INPUTS
	input	clk,
	input	reset,
// Outputs
	output reg Dclk
);
// this is the clock counter that will 
reg [COUNTERSIZE-1:0] cclk;
// clock counter, also counter
always @ (posedge clk) begin
	if (reset) begin
		cclk <= 0;
		Dclk <= 0;
	end else begin
		if (cclk == COUNTERLIMIT) begin
			cclk <= 0;
			Dclk <= ~Dclk;
		end else begin
			cclk <= cclk + 1;
		end
	end
end
endmodule

RAM/DeBounce.v
module DeBounce (
// INPUTS
	input clk,
	input in,
	input reset,
// Outputs
	output reg out
);

reg [2:0] Dclk;

reg [5:0] DB;

reg Dout;

reg state;

always @ (reset) begin
	Dclk <= 0;
	DB <= 0;
	out <= 0;
	state <= 0;
end

always @ (posedge clk & ~reset) begin
	if (Dclk[2:1] == 2'b11) begin
		Dclk[2:1] <= 2'b00;
		Dout = 1;
	end else begin
	Dclk <= Dclk + 1'b1;
	Dout = 0;
	end
end

always @ (posedge Dout & ~reset) begin
	if (state) begin
		if (in == 0) begin
			if (DB[5:4] == 2'b11) begin
				state = 0;
				DB[5:4] <= 2'b00;
				out = 0;
			end else begin
				DB <= DB + 1;
			end
		end
	end else begin
		if (in == 1) begin
			if (DB[5:4] == 2'b11) begin
				state = 1;
				DB[5:4] <= 2'b00;
				out = 1;
			end else begin
				DB <= DB + 1;
			end
		end
	end
end
endmodule

RAM/Sequencer.v
module sequencer(
    input clk,
    input [3:0]pmod,

    output reg [1:0]led
);
DeBounce DeBounce (
// INPUTS
    .reset(reset),
    .in(~pmod[0]),
    .clk(clk),
// Outputs
    .out(PWrite)
);
Clock #(
    .COUNTERSIZE(6),
    .COUNTERLIMIT(6)
) clock  (
// INPUTS
    .clk(clk),
    .reset(reset),
// Outputs
    .Dclk(Dclk)
);
RAM RAM (
// INPUTS
    .reset(reset),
    .clock(clk),
    .read(read),
    .write(write),
    .WriteAddr(WriteAddr),
    .ReadAddr(ReadAddr),
    .WriteData(WriteData),
// Outputs
    .ReadData(ReadData)
);

reg [7:0] WriteData;

wire [7:0] ReadData;

assign reset = ~pmod[3:3];

assign button = ~pmod[2:1];

wire [1:0] button;

reg write;
reg read;
reg ADDRSHIFT;
reg EnWrite;

reg [1:0] WriteAddr;
reg [1:0] ReadAddr;


// make a write semaphor
always @ (posedge reset) begin
    ReadAddr <= -1;
    WriteAddr <= -1;
end
always @ (posedge PWrite & ~PWrite) begin
    EnWrite <= 1;
end
always @ (posedge Dclk) begin
    ADDRSHIFT <= 1;
    ReadAddr <= ReadAddr + 1;
    WriteAddr <= WriteAddr + 1;
end
always @ (posedge clk & ~reset) begin
    if (EnWrite & ~write) begin
        WriteData[1:0] <= button;
        led <= button;
        write <= 1;
    end else begin
        write <= 0;
        EnWrite <= 0;
    end
    if (ADDRSHIFT & ~read) begin
        read <= 1;
        ADDRSHIFT <= 0;
    end else begin
        read <= 0;
        led <= ReadData;
    end
end
endmodule

RAM/TEST_tb.v
`timescale 1ns/10ps
module test();
reg clk = 0;
reg reset = 0;

always begin
    #41.667

    clk = ~clk;
end

initial begin
    #1
    pmod[3:3] = 0;
    #250
    pmod[3:3] = 1;
end

initial begin
    $dumpfile("TEST_tb.vcd");
    $dumpvars(0, test);
    #22000

    $display("Finished");
    $finish;
end
sequencer sequencer(
    .clk(clk),
    .pmod(pmod),

    .led(led)
);
reg [3:0] pmod = 4'b1111;

always begin
    #300
    pmod[1:0] <= $urandom_range(3,0);
end

always begin
    #($urandom_range(400,600));
    pmod[2:2] <= $urandom_range(0,1);
end

endmodule

RAM/TEST_tb.vcd
$date
	Fri Feb 24 12:21:26 2023
$end
$version
	Icarus Verilog
$end
$timescale
	1ps
$end
$scope module test $end
$var wire 1 ! led $end
$var reg 1 " clk $end
$var reg 4 # pmod [3:0] $end
$var reg 1 $ reset $end
$scope module sequencer $end
$var wire 2 % button [1:0] $end
$var wire 1 " clk $end
$var wire 4 & pmod [3:0] $end
$var wire 1 ' reset $end
$var wire 8 ( ReadData [7:0] $end
$var wire 1 ) PWrite $end
$var wire 1 * Dclk $end
$var reg 1 + ADDRSHIFT $end
$var reg 1 , EnWrite $end
$var reg 2 - ReadAddr [1:0] $end
$var reg 2 . WriteAddr [1:0] $end
$var reg 8 / WriteData [7:0] $end
$var reg 2 0 led [1:0] $end
$var reg 1 1 read $end
$var reg 1 2 write $end
$scope module DeBounce $end
$var wire 1 " clk $end
$var wire 1 3 in $end
$var wire 1 ' reset $end
$var reg 6 4 DB [5:0] $end
$var reg 3 5 Dclk [2:0] $end
$var reg 1 6 Dout $end
$var reg 1 ) out $end
$var reg 1 7 state $end
$upscope $end
$scope module RAM $end
$var wire 4 8 ReadAddr [3:0] $end
$var wire 4 9 WriteAddr [3:0] $end
$var wire 8 : WriteData [7:0] $end
$var wire 1 " clock $end
$var wire 1 1 read $end
$var wire 1 ' reset $end
$var wire 1 2 write $end
$var reg 8 ; ReadData [7:0] $end
$var reg 1 < ReadReady $end
$var reg 1 = WriteReady $end
$upscope $end
$scope module clock $end
$var wire 1 " clk $end
$var wire 1 ' reset $end
$var reg 1 * Dclk $end
$var reg 6 > cclk [5:0] $end
$upscope $end
$upscope $end
$upscope $end
$enddefinitions $end
#0
$dumpvars
bx >
x=
x<
bx ;
bx :
b0xx 9
b0xx 8
07
x6
b0 5
b0 4
03
x2
x1
bx 0
bx /
bx .
bx -
x,
x+
x*
0)
bx (
0'
b1111 &
b0 %
0$
b1111 #
0"
x!
$end
#1000
b11 9
b11 .
b11 8
b11 -
0=
0<
1'
b111 #
b111 &
#41670
0*
b0 >
1"
#83340
0"
#125010
1"
#166680
0"
#208350
1"
#250020
0"
#251000
0'
b1111 #
b1111 &
#291690
01
0,
02
b1 5
b1 >
06
1=
1<
1"
#300000
b1 %
b1101 #
b1101 &
#333360
0"
#375030
b10 5
b10 >
1"
#416700
0"
#458370
b11 5
b11 >
1"
#500040
0"
#514000
b11 %
b1001 #
b1001 &
#541710
b100 5
b100 >
1"
#583380
0"
#600000
13
b10 %
b1010 #
b1010 &
#625050
b101 5
b101 >
1"
#666720
0"
#708390
b110 5
b110 >
1"
#750060
0"
#791730
b0 9
b0 .
b0 8
b0 -
1+
b1 4
b0 5
1*
b0 >
16
1"
#833400
0"
#875070
0+
11
b1 5
b1 >
06
1"
#900000
03
b1011 #
b1011 &
#916740
0"
#958410
01
b10 5
b0 (
b0 ;
b10 >
0<
1"
#1000080
0"
#1041750
0!
b0 0
b11 5
b11 >
1<
1"
#1083420
0"
#1125090
b100 5
b100 >
1"
#1166760
0"
#1200000
13
b1010 #
b1010 &
#1208430
b101 5
b101 >
1"
#1250100
0"
#1291770
b110 5
b110 >
1"
#1333440
0"
#1360000
b0 %
b1110 #
b1110 &
#1375110
b10 4
b0 5
0*
b0 >
16
1"
#1416780
0"
#1458450
b1 5
b1 >
06
1"
#1500120
0"
#1541790
b10 5
b10 >
1"
#1583460
0"
#1625130
b11 5
b11 >
1"
#1666800
0"
#1708470
b100 5
b100 >
1"
#1750140
0"
#1791810
b101 5
b101 >
1"
#1800000
03
b1111 #
b1111 &
#1833480
0"
#1875150
b110 5
b110 >
1"
#1916820
0"
#1958490
b1 9
b1 .
b1 8
b1 -
1+
b0 5
1*
b0 >
16
1"
#2000160
0"
#2041830
0+
11
b1 5
b1 >
06
1"
#2083500
0"
#2100000
b1 %
b1101 #
b1101 &
#2125170
01
b10 5
b1 (
b1 ;
b10 >
0<
1"
#2166840
0"
#2208510
1!
b1 0
b11 5
b11 >
1<
1"
#2250180
0"
#2291850
b100 5
b100 >
1"
#2333520
0"
#2375190
b101 5
b101 >
1"
#2416860
0"
#2458530
b110 5
b110 >
1"
#2500200
0"
#2504000
b11 %
b1001 #
b1001 &
#2541870
b0 5
0*
b0 >
16
1"
#2583540
0"
#2625210
b1 5
b1 >
06
1"
#2666880
0"
#2700000
13
b1000 #
b1000 &
#2708550
b10 5
b10 >
1"
#2750220
0"
#2791890
b11 5
b11 >
1"
#2833560
0"
#2875230
b100 5
b100 >
1"
#2916900
0"
#2958570
b101 5
b101 >
1"
#3000240
0"
#3041910
b110 5
b110 >
1"
#3083580
0"
#3094000
b1 %
b1100 #
b1100 &
#3125250
b10 9
b10 .
b10 8
b10 -
1+
b11 4
b0 5
1*
b0 >
16
1"
#3166920
0"
#3208590
0+
11
b1 5
b1 >
06
1"
#3250260
0"
#3291930
01
b10 5
b10 (
b10 ;
b10 >
0<
1"
#3300000
03
b1101 #
b1101 &
#3333600
0"
#3375270
0!
b10 0
b11 5
b11 >
1<
1"
#3416940
0"
#3458610
b100 5
b100 >
1"
#3500280
0"
#3541950
b101 5
b101 >
1"
#3583620
0"
#3625290
b110 5
b110 >
1"
#3666960
0"
#3689000
b11 %
b1001 #
b1001 &
#3708630
b0 5
0*
b0 >
16
1"
#3750300
0"
#3791970
b1 5
b1 >
06
1"
#3833640
0"
#3875310
b10 5
b10 >
1"
#3916980
0"
#3958650
b11 5
b11 >
1"
#4000320
0"
#4041990
b100 5
b100 >
1"
#4083660
0"
#4125330
b101 5
b101 >
1"
#4167000
0"
#4200000
13
b1000 #
b1000 &
#4208670
b110 5
b110 >
1"
#4250340
0"
#4292010
b11 9
b11 .
b11 8
b11 -
1+
b100 4
b0 5
1*
b0 >
16
1"
#4333680
0"
#4375350
0+
11
b1 5
b1 >
06
1"
#4417020
0"
#4458690
01
b10 5
b11 (
b11 ;
b10 >
0<
1"
#4500000
b10 %
b1010 #
b1010 &
#4500360
0"
#4542030
1!
b11 0
b11 5
b11 >
1<
1"
#4583700
0"
#4625370
b100 5
b100 >
1"
#4667040
0"
#4708710
b101 5
b101 >
1"
#4750380
0"
#4792050
b110 5
b110 >
1"
#4800000
03
b1011 #
b1011 &
#4833720
0"
#4875390
b0 5
0*
b0 >
16
1"
#4917060
0"
#4958730
b1 5
b1 >
06
1"
#5000400
0"
#5042070
b10 5
b10 >
1"
#5083740
0"
#5100000
b11 %
b1001 #
b1001 &
#5125410
b11 5
b11 >
1"
#5167080
0"
#5208750
b100 5
b100 >
1"
#5250420
0"
#5292090
b101 5
b101 >
1"
#5333760
0"
#5375430
b110 5
b110 >
1"
#5400000
13
b1000 #
b1000 &
#5417100
0"
#5458770
b0 9
b0 .
b0 8
b0 -
1+
b101 4
b0 5
1*
b0 >
16
1"
#5500440
0"
#5542110
0+
11
b1 5
b1 >
06
1"
#5583780
0"
#5625450
01
b10 5
b0 (
b0 ;
b10 >
0<
1"
#5667120
0"
#5700000
03
b1001 #
b1001 &
#5708790
0!
b0 0
b11 5
b11 >
1<
1"
#5750460
0"
#5792130
b100 5
b100 >
1"
#5833800
0"
#5875470
b101 5
b101 >
1"
#5917140
0"
#5958810
b110 5
b110 >
1"
#6000000
13
b1000 #
b1000 &
#6000480
0"
#6042150
b110 4
b0 5
0*
b0 >
16
1"
#6083820
0"
#6125490
b1 5
b1 >
06
1"
#6167160
0"
#6208830
b10 5
b10 >
1"
#6250500
0"
#6292170
b11 5
b11 >
1"
#6300000
03
b1001 #
b1001 &
#6333840
0"
#6375510
b100 5
b100 >
1"
#6417180
0"
#6458850
b101 5
b101 >
1"
#6500520
0"
#6542190
b110 5
b110 >
1"
#6583860
0"
#6600000
13
b10 %
b1010 #
b1010 &
#6625530
b1 9
b1 .
b1 8
b1 -
1+
b111 4
b0 5
1*
b0 >
16
1"
#6638000
b0 %
b1110 #
b1110 &
#6667200
0"
#6708870
0+
11
b1 5
b1 >
06
1"
#6750540
0"
#6792210
01
b10 5
b1 (
b1 ;
b10 >
0<
1"
#6833880
0"
#6875550
1!
b1 0
b11 5
b11 >
1<
1"
#6900000
b1 %
b1100 #
b1100 &
#6917220
0"
#6958890
b100 5
b100 >
1"
#7000560
0"
#7042230
b101 5
b101 >
1"
#7083900
0"
#7125570
b110 5
b110 >
1"
#7167240
0"
#7200000
b0 %
b1110 #
b1110 &
#7208910
b1000 4
b0 5
0*
b0 >
16
1"
#7250580
0"
#7292250
b1 5
b1 >
06
1"
#7333920
0"
#7375590
b10 5
b10 >
1"
#7417260
0"
#7458930
b11 5
b11 >
1"
#7500000
03
b1 %
b1101 #
b1101 &
#7500600
0"
#7542270
b100 5
b100 >
1"
#7583940
0"
#7625610
b101 5
b101 >
1"
#7667280
0"
#7708950
b110 5
b110 >
1"
#7750620
0"
#7792290
b10 9
b10 .
b10 8
b10 -
1+
b0 5
1*
b0 >
16
1"
#7800000
b0 %
b1111 #
b1111 &
#7833960
0"
#7875630
0+
11
b1 5
b1 >
06
1"
#7917300
0"
#7958970
01
b10 5
b10 (
b10 ;
b10 >
0<
1"
#8000640
0"
#8042310
0!
b10 0
b11 5
b11 >
1<
1"
#8083980
0"
#8125650
b100 5
b100 >
1"
#8167320
0"
#8208990
b101 5
b101 >
1"
#8250660
0"
#8292330
b110 5
b110 >
1"
#8334000
0"
#8375670
b0 5
0*
b0 >
16
1"
#8400000
b1 %
b1101 #
b1101 &
#8417340
0"
#8459010
b1 5
b1 >
06
1"
#8500680
0"
#8542350
b10 5
b10 >
1"
#8584020
0"
#8625690
b11 5
b11 >
1"
#8667360
0"
#8700000
13
b1100 #
b1100 &
#8709030
b100 5
b100 >
1"
#8750700
0"
#8792370
b101 5
b101 >
1"
#8834040
0"
#8875710
b110 5
b110 >
1"
#8917380
0"
#8959050
b11 9
b11 .
b11 8
b11 -
1+
b1001 4
b0 5
1*
b0 >
16
1"
#9000000
03
b0 %
b1111 #
b1111 &
#9000720
0"
#9042390
0+
11
b1 5
b1 >
06
1"
#9084060
0"
#9125730
01
b10 5
b11 (
b11 ;
b10 >
0<
1"
#9167400
0"
#9209070
1!
b11 0
b11 5
b11 >
1<
1"
#9250740
0"
#9292410
b100 5
b100 >
1"
#9300000
13
b1110 #
b1110 &
#9334080
0"
#9375750
b101 5
b101 >
1"
#9417420
0"
#9459090
b110 5
b110 >
1"
#9500760
0"
#9519000
b10 %
b1010 #
b1010 &
#9542430
b1010 4
b0 5
0*
b0 >
16
1"
#9584100
0"
#9600000
03
b1011 #
b1011 &
#9625770
b1 5
b1 >
06
1"
#9667440
0"
#9709110
b10 5
b10 >
1"
#9750780
0"
#9792450
b11 5
b11 >
1"
#9834120
0"
#9875790
b100 5
b100 >
1"
#9917460
0"
#9959130
b101 5
b101 >
1"
#10000800
0"
#10027000
b0 %
b1111 #
b1111 &
#10042470
b110 5
b110 >
1"
#10084140
0"
#10125810
b0 9
b0 .
b0 8
b0 -
1+
b0 5
1*
b0 >
16
1"
#10167480
0"
#10209150
0+
11
b1 5
b1 >
06
1"
#10250820
0"
#10292490
01
b10 5
b0 (
b0 ;
b10 >
0<
1"
#10334160
0"
#10375830
0!
b0 0
b11 5
b11 >
1<
1"
#10417500
0"
#10459170
b100 5
b100 >
1"
#10500840
0"
#10542510
b101 5
b101 >
1"
#10584180
0"
#10625850
b110 5
b110 >
1"
#10667520
0"
#10709190
b0 5
0*
b0 >
16
1"
#10750860
0"
#10792530
b1 5
b1 >
06
1"
#10800000
b1 %
b1101 #
b1101 &
#10834200
0"
#10875870
b10 5
b10 >
1"
#10917540
0"
#10959210
b11 5
b11 >
1"
#11000880
0"
#11029000
b11 %
b1001 #
b1001 &
#11042550
b100 5
b100 >
1"
#11084220
0"
#11100000
b10 %
b1011 #
b1011 &
#11125890
b101 5
b101 >
1"
#11167560
0"
#11209230
b110 5
b110 >
1"
#11250900
0"
#11292570
b1 9
b1 .
b1 8
b1 -
1+
b0 5
1*
b0 >
16
1"
#11334240
0"
#11375910
0+
11
b1 5
b1 >
06
1"
#11400000
13
b11 %
b1000 #
b1000 &
#11417580
0"
#11459250
01
b10 5
b1 (
b1 ;
b10 >
0<
1"
#11500920
0"
#11542590
1!
b1 0
b11 5
b11 >
1<
1"
#11584260
0"
#11625930
b100 5
b100 >
1"
#11667600
0"
#11709270
b101 5
b101 >
1"
#11750940
0"
#11792610
b110 5
b110 >
1"
#11834280
0"
#11875950
b1011 4
b0 5
0*
b0 >
16
1"
#11917620
0"
#11948000
b1 %
b1100 #
b1100 &
#11959290
b1 5
b1 >
06
1"
#12000000
03
b1101 #
b1101 &
#12000960
0"
#12042630
b10 5
b10 >
1"
#12084300
0"
#12125970
b11 5
b11 >
1"
#12167640
0"
#12209310
b100 5
b100 >
1"
#12250980
0"
#12292650
b101 5
b101 >
1"
#12300000
b0 %
b1111 #
b1111 &
#12334320
0"
#12375990
b110 5
b110 >
1"
#12417660
0"
#12453000
b10 %
b1011 #
b1011 &
#12459330
b10 9
b10 .
b10 8
b10 -
1+
b0 5
1*
b0 >
16
1"
#12501000
0"
#12542670
0+
11
b1 5
b1 >
06
1"
#12584340
0"
#12600000
13
b1010 #
b1010 &
#12626010
01
b10 5
b10 (
b10 ;
b10 >
0<
1"
#12667680
0"
#12709350
0!
b10 0
b11 5
b11 >
1<
1"
#12751020
0"
#12792690
b100 5
b100 >
1"
#12834360
0"
#12876030
b101 5
b101 >
1"
#12900000
b11 %
b1000 #
b1000 &
#12917700
0"
#12959370
b110 5
b110 >
1"
#12977000
b1 %
b1100 #
b1100 &
#13001040
0"
#13042710
b1100 4
b0 5
0*
b0 >
16
1"
#13084380
0"
#13126050
b1 5
b1 >
06
1"
#13167720
0"
#13200000
b0 %
b1110 #
b1110 &
#13209390
b10 5
b10 >
1"
#13251060
0"
#13292730
b11 5
b11 >
1"
#13334400
0"
#13376070
b100 5
b100 >
1"
#13417740
0"
#13459410
b101 5
b101 >
1"
#13500000
b11 %
b1000 #
b1000 &
#13501080
0"
#13542750
b110 5
b110 >
1"
#13584420
0"
#13626090
b11 9
b11 .
b11 8
b11 -
1+
b1101 4
b0 5
1*
b0 >
16
1"
#13667760
0"
#13709430
0+
11
b1 5
b1 >
06
1"
#13751100
0"
#13792770
01
b10 5
b11 (
b11 ;
b10 >
0<
1"
#13800000
b10 %
b1010 #
b1010 &
#13834440
0"
#13876110
1!
b11 0
b11 5
b11 >
1<
1"
#13917780
0"
#13959450
b100 5
b100 >
1"
#14001120
0"
#14042790
b101 5
b101 >
1"
#14052000
b0 %
b1110 #
b1110 &
#14084460
0"
#14126130
b110 5
b110 >
1"
#14167800
0"
#14209470
b1110 4
b0 5
0*
b0 >
16
1"
#14251140
0"
#14292810
b1 5
b1 >
06
1"
#14334480
0"
#14376150
b10 5
b10 >
1"
#14417820
0"
#14459490
b11 5
b11 >
1"
#14477000
b10 %
b1010 #
b1010 &
#14501160
0"
#14542830
b100 5
b100 >
1"
#14584500
0"
#14626170
b101 5
b101 >
1"
#14667840
0"
#14700000
03
b11 %
b1001 #
b1001 &
#14709510
b110 5
b110 >
1"
#14751180
0"
#14792850
b0 9
b0 .
b0 8
b0 -
1+
b0 5
1*
b0 >
16
1"
#14834520
0"
#14876190
0+
11
b1 5
b1 >
06
1"
#14917860
0"
#14932000
b1 %
b1101 #
b1101 &
#14959530
01
b10 5
b0 (
b0 ;
b10 >
0<
1"
#15000000
13
b0 %
b1110 #
b1110 &
#15001200
0"
#15042870
0!
b0 0
b11 5
b11 >
1<
1"
#15084540
0"
#15126210
b100 5
b100 >
1"
#15167880
0"
#15209550
b101 5
b101 >
1"
#15251220
0"
#15292890
b110 5
b110 >
1"
#15300000
03
b1 %
b1101 #
b1101 &
#15334560
0"
#15347000
b11 %
b1001 #
b1001 &
#15376230
b0 5
0*
b0 >
16
1"
#15417900
0"
#15459570
b1 5
b1 >
06
1"
#15501240
0"
#15542910
b10 5
b10 >
1"
#15584580
0"
#15600000
13
b1000 #
b1000 &
#15626250
b11 5
b11 >
1"
#15667920
0"
#15709590
b100 5
b100 >
1"
#15751260
0"
#15792930
b101 5
b101 >
1"
#15817000
b1 %
b1100 #
b1100 &
#15834600
0"
#15876270
b110 5
b110 >
1"
#15900000
03
b1101 #
b1101 &
#15917940
0"
#15959610
b1 9
b1 .
b1 8
b1 -
1+
b0 5
1*
b0 >
16
1"
#16001280
0"
#16042950
0+
11
b1 5
b1 >
06
1"
#16084620
0"
#16126290
01
b10 5
b1 (
b1 ;
b10 >
0<
1"
#16167960
0"
#16209630
1!
b1 0
b11 5
b11 >
1<
1"
#16251300
0"
#16292970
b100 5
b100 >
1"
#16334640
0"
#16376310
b101 5
b101 >
1"
#16417980
0"
#16459650
b110 5
b110 >
1"
#16501320
0"
#16542990
b0 5
0*
b0 >
16
1"
#16584660
0"
#16626330
b1 5
b1 >
06
1"
#16668000
0"
#16709670
b10 5
b10 >
1"
#16751340
0"
#16793010
b11 5
b11 >
1"
#16834680
0"
#16876350
b100 5
b100 >
1"
#16918020
0"
#16930000
b11 %
b1001 #
b1001 &
#16959690
b101 5
b101 >
1"
#17001360
0"
#17043030
b110 5
b110 >
1"
#17084700
0"
#17126370
b10 9
b10 .
b10 8
b10 -
1+
b0 5
1*
b0 >
16
1"
#17168040
0"
#17209710
0+
11
b1 5
b1 >
06
1"
#17251380
0"
#17293050
01
b10 5
b10 (
b10 ;
b10 >
0<
1"
#17334720
0"
#17376390
0!
b10 0
b11 5
b11 >
1<
1"
#17400000
13
b10 %
b1010 #
b1010 &
#17401000
b0 %
b1110 #
b1110 &
#17418060
0"
#17459730
b100 5
b100 >
1"
#17501400
0"
#17543070
b101 5
b101 >
1"
#17584740
0"
#17626410
b110 5
b110 >
1"
#17668080
0"
#17709750
b1111 4
b0 5
0*
b0 >
16
1"
#17751420
0"
#17793090
b1 5
b1 >
06
1"
#17834760
0"
#17876430
b10 5
b10 >
1"
#17918100
0"
#17959770
b11 5
b11 >
1"
#18000000
03
b1111 #
b1111 &
#18001440
0"
#18043110
b100 5
b100 >
1"
#18084780
0"
#18126450
b101 5
b101 >
1"
#18168120
0"
#18209790
b110 5
b110 >
1"
#18251460
0"
#18293130
b11 9
b11 .
b11 8
b11 -
1+
b0 5
1*
b0 >
16
1"
#18300000
b1 %
b1101 #
b1101 &
#18334800
0"
#18376470
0+
11
b1 5
b1 >
06
1"
#18389000
b11 %
b1001 #
b1001 &
#18418140
0"
#18459810
01
b10 5
b11 (
b11 ;
b10 >
0<
1"
#18501480
0"
#18543150
1!
b11 0
b11 5
b11 >
1<
1"
#18584820
0"
#18600000
13
b10 %
b1010 #
b1010 &
#18626490
b100 5
b100 >
1"
#18668160
0"
#18709830
b101 5
b101 >
1"
#18751500
0"
#18793170
b110 5
b110 >
1"
#18834840
0"
#18865000
b0 %
b1110 #
b1110 &
#18876510
b10000 4
b0 5
0*
b0 >
16
1"
#18900000
b1 %
b1100 #
b1100 &
#18918180
0"
#18959850
b1 5
b1 >
06
1"
#19001520
0"
#19043190
b10 5
b10 >
1"
#19084860
0"
#19126530
b11 5
b11 >
1"
#19168200
0"
#19200000
03
b0 %
b1111 #
b1111 &
#19209870
b100 5
b100 >
1"
#19251540
0"
#19293210
b101 5
b101 >
1"
#19305000
b10 %
b1011 #
b1011 &
#19334880
0"
#19376550
b110 5
b110 >
1"
#19418220
0"
#19459890
b0 9
b0 .
b0 8
b0 -
1+
b0 5
1*
b0 >
16
1"
#19500000
b11 %
b1001 #
b1001 &
#19501560
0"
#19543230
0+
11
b1 5
b1 >
06
1"
#19584900
0"
#19626570
01
b10 5
b0 (
b0 ;
b10 >
0<
1"
#19668240
0"
#19709910
0!
b0 0
b11 5
b11 >
1<
1"
#19751580
0"
#19793250
b100 5
b100 >
1"
#19800000
b10 %
b1011 #
b1011 &
#19834920
0"
#19853000
b0 %
b1111 #
b1111 &
#19876590
b101 5
b101 >
1"
#19918260
0"
#19959930
b110 5
b110 >
1"
#20001600
0"
#20043270
b0 5
0*
b0 >
16
1"
#20084940
0"
#20100000
13
b1 %
b1100 #
b1100 &
#20126610
b1 5
b1 >
06
1"
#20168280
0"
#20209950
b10 5
b10 >
1"
#20251620
0"
#20293290
b11 5
b11 >
1"
#20334960
0"
#20376630
b100 5
b100 >
1"
#20400000
03
b0 %
b1111 #
b1111 &
#20418300
0"
#20459970
b101 5
b101 >
1"
#20501640
0"
#20543310
b110 5
b110 >
1"
#20584980
0"
#20626650
b1 9
b1 .
b1 8
b1 -
1+
b0 5
1*
b0 >
16
1"
#20668320
0"
#20684000
b10 %
b1011 #
b1011 &
#20709990
0+
11
b1 5
b1 >
06
1"
#20751660
0"
#20793330
01
b10 5
b1 (
b1 ;
b10 >
0<
1"
#20835000
0"
#20876670
1!
b1 0
b11 5
b11 >
1<
1"
#20918340
0"
#20960010
b100 5
b100 >
1"
#21001680
0"
#21043350
b101 5
b101 >
1"
#21085020
0"
#21126690
b110 5
b110 >
1"
#21130000
b0 %
b1111 #
b1111 &
#21168360
0"
#21210030
b0 5
0*
b0 >
16
1"
#21251700
0"
#21293370
b1 5
b1 >
06
1"
#21300000
13
b1110 #
b1110 &
#21335040
0"
#21376710
b10 5
b10 >
1"
#21418380
0"
#21460050
b11 5
b11 >
1"
#21501720
0"
#21543390
b100 5
b100 >
1"
#21585060
0"
#21600000
03
b1 %
b1101 #
b1101 &
#21626730
b101 5
b101 >
1"
#21668400
0"
#21710070
b110 5
b110 >
1"
#21751740
0"
#21793410
b10 9
b10 .
b10 8
b10 -
1+
b0 5
1*
b0 >
16
1"
#21835080
0"
#21876750
0+
11
b1 5
b1 >
06
1"
#21900000
b0 %
b1111 #
b1111 &
#21918420
0"
#21960090
01
b10 5
b10 (
b10 ;
b10 >
0<
1"
