RAM/RAM/RAM.v
module RAM # (
    parameter INIT = "MEMINIT.txt"
) (
// INPUTS
input wire reset,
input wire clock,
input wire read,
input wire write,
input wire [3:0] WriteAddr,
input wire [3:0] ReadAddr,
input wire [7:0] WriteData,
// Outputs
output reg [7:0] ReadData,
output reg ReadReady,
output reg WriteReady
);

reg [7:0] mem [0:15];

always @ (posedge clock or posedge reset) begin
    if (reset) begin
        ReadReady <= 0;
        WriteReady <= 0;
        $readmemh(INIT, mem);
    end else begin
        if (read) begin
            ReadData <= mem[ReadAddr];
            ReadReady <= 0;
        end else begin
            ReadReady <= 1;
        end        
        if (write) begin
            mem[WriteAddr] <= WriteData;
            WriteReady <= 0;
        end else begin
            WriteReady <= 1;
        end
    end
end
endmodule

RAM/RAM/TEST_tb.v
`timescale 1ns/10ps
module test();
reg clk = 1;
reg slwclk = 1;
reg reset = 0;

always begin
    #41.667

    clk <= ~clk;
end
always begin
    #416.67

    slwclk <= ~slwclk;
end

initial begin
    #1
    reset <= 1;
    #250
    reset <= 0;
end

initial begin
    $dumpfile("TEST_tb.vcd");
    $dumpvars(0, test);
    #22000

    $display("Finished");
    $finish;
end

always @ (posedge WriteReady or negedge WriteReady) begin
    if (WriteReady) begin
        WriteAddr <= WriteAddr + 1;
        WriteData <= $urandom_range(255,0);
        write <= 1;
    end else begin
        write <= 0;
    end
end
always @ (posedge clk) begin
    if (ready) begin
        read <= 1;
        ReadAddr <= ReadAddr + 1;
        ready <= 0;
    end else if (ReadReady) begin
        Data <= ReadData;
        read <= 0;
    end
end
always @ (posedge slwclk) begin
    ready <= 1;
end
RAM RAM(
    .clock(clk),
    .WriteReady(WriteReady),
    .ReadReady(ReadReady),
    .write(write),
    .read(read),
    .WriteAddr(WriteAddr),
    .ReadAddr(ReadAddr),
    .WriteData(WriteData),
    .ReadData(ReadData),
    .reset(reset)
);
reg [0:0] write = 0;
reg [0:0] read = 0;

reg [7:0] Data;

reg ready;

reg counter = 1'b0;

reg [3:0] WriteAddr = 4'b0000;
reg [3:0] ReadAddr = 4'b0000;
reg [7:0] WriteData = 8'b0000000;
wire [7:0] ReadData;
wire WriteReady;
wire ReadReady;
wire TechReadReady;

endmodule

RAM/RAM/TEST_tb.vcd
$date
	Sun Feb 19 16:44:15 2023
$end
$version
	Icarus Verilog
$end
$timescale
	1ps
$end
$scope module test $end
$var wire 1 ! WriteReady $end
$var wire 1 " ReadReady $end
$var wire 8 # ReadData [7:0] $end
$var reg 8 $ Data [7:0] $end
$var reg 4 % ReadAddr [3:0] $end
$var reg 4 & WriteAddr [3:0] $end
$var reg 8 ' WriteData [7:0] $end
$var reg 1 ( clk $end
$var reg 1 ) counter $end
$var reg 1 * read $end
$var reg 1 + ready $end
$var reg 1 , reset $end
$var reg 1 - slwclk $end
$var reg 1 . write $end
$scope module RAM $end
$var wire 4 / ReadAddr [3:0] $end
$var wire 4 0 WriteAddr [3:0] $end
$var wire 8 1 WriteData [7:0] $end
$var wire 1 ( clock $end
$var wire 1 * read $end
$var wire 1 , reset $end
$var wire 1 . write $end
$var reg 8 2 ReadData [7:0] $end
$var reg 1 " ReadReady $end
$var reg 1 ! WriteReady $end
$upscope $end
$upscope $end
$enddefinitions $end
#0
$dumpvars
bx 2
b10010010 1
b1 0
b0 /
1.
1-
0,
x+
0*
0)
1(
b10010010 '
b1 &
b0 %
bx $
bx #
1"
1!
$end
#1000
0.
0!
0"
1,
#41670
0(
#83340
1(
#125010
0(
#166680
1(
#208350
0(
#250020
1(
#251000
0,
#291690
0(
#333360
1.
b1000000 '
b1000000 1
b10 &
b10 0
1!
1"
1(
#375030
0(
#416670
0-
#416700
0.
0!
1(
#458370
0(
#500040
1.
b100 '
b100 1
b11 &
b11 0
1!
1(
#541710
0(
#583380
0.
0!
1(
#625050
0(
#666720
1.
b110001 '
b110001 1
b100 &
b100 0
1!
1(
#708390
0(
#750060
0.
0!
1(
#791730
0(
#833340
1+
1-
#833400
1.
b10000110 '
b10000110 1
b101 &
b101 0
1!
0+
b1 %
b1 /
1*
1(
#875070
0(
#916740
0.
0!
0"
b1 #
b1 2
0*
1(
#958410
0(
#1000080
1.
b11000110 '
b11000110 1
b110 &
b110 0
1!
1"
1(
#1041750
0(
#1083420
0.
0!
b1 $
1(
#1125090
0(
#1166760
1.
b110010 '
b110010 1
b111 &
b111 0
1!
1(
#1208430
0(
#1250010
0-
#1250100
0.
0!
1(
#1291770
0(
#1333440
1.
b1001 '
b1001 1
b1000 &
b1000 0
1!
1(
#1375110
0(
#1416780
0.
0!
1(
#1458450
0(
#1500120
1.
b10000000 '
b10000000 1
b1001 &
b1001 0
1!
1(
#1541790
0(
#1583460
0.
0!
1(
#1625130
0(
#1666680
1+
1-
#1666800
1.
b10000110 '
b10000110 1
b1010 &
b1010 0
1!
0+
b10 %
b10 /
1*
1(
#1708470
0(
#1750140
0.
0!
0"
b1000000 #
b1000000 2
0*
1(
#1791810
0(
#1833480
1.
b10111011 '
b10111011 1
b1011 &
b1011 0
1!
1"
1(
#1875150
0(
#1916820
0.
0!
b1000000 $
1(
#1958490
0(
#2000160
1.
b10011110 '
b10011110 1
b1100 &
b1100 0
1!
1(
#2041830
0(
#2083350
0-
#2083500
0.
0!
1(
#2125170
0(
#2166840
1.
b11110110 '
b11110110 1
b1101 &
b1101 0
1!
1(
#2208510
0(
#2250180
0.
0!
1(
#2291850
0(
#2333520
1.
b11000110 '
b11000110 1
b1110 &
b1110 0
1!
1(
#2375190
0(
#2416860
0.
0!
1(
#2458530
0(
#2500020
1+
1-
#2500200
1.
b11111100 '
b11111100 1
b1111 &
b1111 0
1!
0+
b11 %
b11 /
1*
1(
#2541870
0(
#2583540
0.
0!
0"
b100 #
b100 2
0*
1(
#2625210
0(
#2666880
1.
b1100011 '
b1100011 1
b0 &
b0 0
1!
1"
1(
#2708550
0(
#2750220
0.
0!
b100 $
1(
#2791890
0(
#2833560
1.
b1100010 '
b1100010 1
b1 &
b1 0
1!
1(
#2875230
0(
#2916690
0-
#2916900
0.
0!
1(
#2958570
0(
#3000240
1.
b1010101 '
b1010101 1
b10 &
b10 0
1!
1(
#3041910
0(
#3083580
0.
0!
1(
#3125250
0(
#3166920
1.
b11110010 '
b11110010 1
b11 &
b11 0
1!
1(
#3208590
0(
#3250260
0.
0!
1(
#3291930
0(
#3333360
1+
1-
#3333600
1.
b111011 '
b111011 1
b100 &
b100 0
1!
0+
b100 %
b100 /
1*
1(
#3375270
0(
#3416940
0.
0!
0"
b110001 #
b110001 2
0*
1(
#3458610
0(
#3500280
1.
b1001 '
b1001 1
b101 &
b101 0
1!
1"
1(
#3541950
0(
#3583620
0.
0!
b110001 $
1(
#3625290
0(
#3666960
1.
b11000111 '
b11000111 1
b110 &
b110 0
1!
1(
#3708630
0(
#3750030
0-
#3750300
0.
0!
1(
#3791970
0(
#3833640
1.
b11111001 '
b11111001 1
b111 &
b111 0
1!
1(
#3875310
0(
#3916980
0.
0!
1(
#3958650
0(
#4000320
1.
b1100111 '
b1100111 1
b1000 &
b1000 0
1!
1(
#4041990
0(
#4083660
0.
0!
1(
#4125330
0(
#4166700
1+
1-
#4167000
1.
b1110100 '
b1110100 1
b1001 &
b1001 0
1!
0+
b101 %
b101 /
1*
1(
#4208670
0(
#4250340
0.
0!
0"
b1001 #
b1001 2
0*
1(
#4292010
0(
#4333680
1.
b1100010 '
b1100010 1
b1010 &
b1010 0
1!
1"
1(
#4375350
0(
#4417020
0.
0!
b1001 $
1(
#4458690
0(
#4500360
1.
b10101110 '
b10101110 1
b1011 &
b1011 0
1!
1(
#4542030
0(
#4583370
0-
#4583700
0.
0!
1(
#4625370
0(
#4667040
1.
b1011110 '
b1011110 1
b1100 &
b1100 0
1!
1(
#4708710
0(
#4750380
0.
0!
1(
#4792050
0(
#4833720
1.
b10110 '
b10110 1
b1101 &
b1101 0
1!
1(
#4875390
0(
#4917060
0.
0!
1(
#4958730
0(
#5000040
1+
1-
#5000400
1.
b110010 '
b110010 1
b1110 &
b1110 0
1!
0+
b110 %
b110 /
1*
1(
#5042070
0(
#5083740
0.
0!
0"
b11000111 #
b11000111 2
0*
1(
#5125410
0(
#5167080
1.
b110001 '
b110001 1
b1111 &
b1111 0
1!
1"
1(
#5208750
0(
#5250420
0.
0!
b11000111 $
1(
#5292090
0(
#5333760
1.
b10000101 '
b10000101 1
b0 &
b0 0
1!
1(
#5375430
0(
#5416710
0-
#5417100
0.
0!
1(
#5458770
0(
#5500440
1.
b1000000 '
b1000000 1
b1 &
b1 0
1!
1(
#5542110
0(
#5583780
0.
0!
1(
#5625450
0(
#5667120
1.
b10010000 '
b10010000 1
b10 &
b10 0
1!
1(
#5708790
0(
#5750460
0.
0!
1(
#5792130
0(
#5833380
1+
1-
#5833800
1.
b11010101 '
b11010101 1
b11 &
b11 0
1!
0+
b111 %
b111 /
1*
1(
#5875470
0(
#5917140
0.
0!
0"
b11111001 #
b11111001 2
0*
1(
#5958810
0(
#6000480
1.
b1001110 '
b1001110 1
b100 &
b100 0
1!
1"
1(
#6042150
0(
#6083820
0.
0!
b11111001 $
1(
#6125490
0(
#6167160
1.
b1001011 '
b1001011 1
b101 &
b101 0
1!
1(
#6208830
0(
#6250050
0-
#6250500
0.
0!
1(
#6292170
0(
#6333840
1.
b1001 '
b1001 1
b110 &
b110 0
1!
1(
#6375510
0(
#6417180
0.
0!
1(
#6458850
0(
#6500520
1.
b110 '
b110 1
b111 &
b111 0
1!
1(
#6542190
0(
#6583860
0.
0!
1(
#6625530
0(
#6666720
1+
1-
#6667200
1.
b101001 '
b101001 1
b1000 &
b1000 0
1!
0+
b1000 %
b1000 /
1*
1(
#6708870
0(
#6750540
0.
0!
0"
b1100111 #
b1100111 2
0*
1(
#6792210
0(
#6833880
1.
b10110101 '
b10110101 1
b1001 &
b1001 0
1!
1"
1(
#6875550
0(
#6917220
0.
0!
b1100111 $
1(
#6958890
0(
#7000560
1.
b1101010 '
b1101010 1
b1010 &
b1010 0
1!
1(
#7042230
0(
#7083390
0-
#7083900
0.
0!
1(
#7125570
0(
#7167240
1.
b1 '
b1 1
b1011 &
b1011 0
1!
1(
#7208910
0(
#7250580
0.
0!
1(
#7292250
0(
#7333920
1.
b1010111 '
b1010111 1
b1100 &
b1100 0
1!
1(
#7375590
0(
#7417260
0.
0!
1(
#7458930
0(
#7500060
1+
1-
#7500600
1.
b10001110 '
b10001110 1
b1101 &
b1101 0
1!
0+
b1001 %
b1001 /
1*
1(
#7542270
0(
#7583940
0.
0!
0"
b10110101 #
b10110101 2
0*
1(
#7625610
0(
#7667280
1.
b1100111 '
b1100111 1
b1110 &
b1110 0
1!
1"
1(
#7708950
0(
#7750620
0.
0!
b10110101 $
1(
#7792290
0(
#7833960
1.
b10010001 '
b10010001 1
b1111 &
b1111 0
1!
1(
#7875630
0(
#7916730
0-
#7917300
0.
0!
1(
#7958970
0(
#8000640
1.
b10000101 '
b10000101 1
b0 &
b0 0
1!
1(
#8042310
0(
#8083980
0.
0!
1(
#8125650
0(
#8167320
1.
b1100101 '
b1100101 1
b1 &
b1 0
1!
1(
#8208990
0(
#8250660
0.
0!
1(
#8292330
0(
#8333400
1+
1-
#8334000
1.
b11110 '
b11110 1
b10 &
b10 0
1!
0+
b1010 %
b1010 /
1*
1(
#8375670
0(
#8417340
0.
0!
0"
b1101010 #
b1101010 2
0*
1(
#8459010
0(
#8500680
1.
b11111001 '
b11111001 1
b11 &
b11 0
1!
1"
1(
#8542350
0(
#8584020
0.
0!
b1101010 $
1(
#8625690
0(
#8667360
1.
b11000101 '
b11000101 1
b100 &
b100 0
1!
1(
#8709030
0(
#8750070
0-
#8750700
0.
0!
1(
#8792370
0(
#8834040
1.
b10100000 '
b10100000 1
b101 &
b101 0
1!
1(
#8875710
0(
#8917380
0.
0!
1(
#8959050
0(
#9000720
1.
b1101100 '
b1101100 1
b110 &
b110 0
1!
1(
#9042390
0(
#9084060
0.
0!
1(
#9125730
0(
#9166740
1+
1-
#9167400
1.
b10111100 '
b10111100 1
b111 &
b111 0
1!
0+
b1011 %
b1011 /
1*
1(
#9209070
0(
#9250740
0.
0!
0"
b1 #
b1 2
0*
1(
#9292410
0(
#9334080
1.
b1000100 '
b1000100 1
b1000 &
b1000 0
1!
1"
1(
#9375750
0(
#9417420
0.
0!
b1 $
1(
#9459090
0(
#9500760
1.
b11110101 '
b11110101 1
b1001 &
b1001 0
1!
1(
#9542430
0(
#9583410
0-
#9584100
0.
0!
1(
#9625770
0(
#9667440
1.
b11011011 '
b11011011 1
b1010 &
b1010 0
1!
1(
#9709110
0(
#9750780
0.
0!
1(
#9792450
0(
#9834120
1.
b11100011 '
b11100011 1
b1011 &
b1011 0
1!
1(
#9875790
0(
#9917460
0.
0!
1(
#9959130
0(
#10000080
1+
1-
#10000800
1.
b11010111 '
b11010111 1
b1100 &
b1100 0
1!
0+
b1100 %
b1100 /
1*
1(
#10042470
0(
#10084140
0.
0!
0"
b1010111 #
b1010111 2
0*
1(
#10125810
0(
#10167480
1.
b1011110 '
b1011110 1
b1101 &
b1101 0
1!
1"
1(
#10209150
0(
#10250820
0.
0!
b1010111 $
1(
#10292490
0(
#10334160
1.
b10010101 '
b10010101 1
b1110 &
b1110 0
1!
1(
#10375830
0(
#10416750
0-
#10417500
0.
0!
1(
#10459170
0(
#10500840
1.
b101 '
b101 1
b1111 &
b1111 0
1!
1(
#10542510
0(
#10584180
0.
0!
1(
#10625850
0(
#10667520
1.
b111000 '
b111000 1
b0 &
b0 0
1!
1(
#10709190
0(
#10750860
0.
0!
1(
#10792530
0(
#10833420
1+
1-
#10834200
1.
b11000010 '
b11000010 1
b1 &
b1 0
1!
0+
b1101 %
b1101 /
1*
1(
#10875870
0(
#10917540
0.
0!
0"
b1011110 #
b1011110 2
0*
1(
#10959210
0(
#11000880
1.
b10100111 '
b10100111 1
b10 &
b10 0
1!
1"
1(
#11042550
0(
#11084220
0.
0!
b1011110 $
1(
#11125890
0(
#11167560
1.
b11101 '
b11101 1
b11 &
b11 0
1!
1(
#11209230
0(
#11250090
0-
#11250900
0.
0!
1(
#11292570
0(
#11334240
1.
b10011101 '
b10011101 1
b100 &
b100 0
1!
1(
#11375910
0(
#11417580
0.
0!
1(
#11459250
0(
#11500920
1.
b111111 '
b111111 1
b101 &
b101 0
1!
1(
#11542590
0(
#11584260
0.
0!
1(
#11625930
0(
#11666760
1+
1-
#11667600
1.
b10001010 '
b10001010 1
b110 &
b110 0
1!
0+
b1110 %
b1110 /
1*
1(
#11709270
0(
#11750940
0.
0!
0"
b10010101 #
b10010101 2
0*
1(
#11792610
0(
#11834280
1.
b11111000 '
b11111000 1
b111 &
b111 0
1!
1"
1(
#11875950
0(
#11917620
0.
0!
b10010101 $
1(
#11959290
0(
#12000960
1.
b11101100 '
b11101100 1
b1000 &
b1000 0
1!
1(
#12042630
0(
#12083430
0-
#12084300
0.
0!
1(
#12125970
0(
#12167640
1.
b10110001 '
b10110001 1
b1001 &
b1001 0
1!
1(
#12209310
0(
#12250980
0.
0!
1(
#12292650
0(
#12334320
1.
b10100110 '
b10100110 1
b1010 &
b1010 0
1!
1(
#12375990
0(
#12417660
0.
0!
1(
#12459330
0(
#12500100
1+
1-
#12501000
1.
b11001111 '
b11001111 1
b1011 &
b1011 0
1!
0+
b1111 %
b1111 /
1*
1(
#12542670
0(
#12584340
0.
0!
0"
b101 #
b101 2
0*
1(
#12626010
0(
#12667680
1.
b11000111 '
b11000111 1
b1100 &
b1100 0
1!
1"
1(
#12709350
0(
#12751020
0.
0!
b101 $
1(
#12792690
0(
#12834360
1.
b11111100 '
b11111100 1
b1101 &
b1101 0
1!
1(
#12876030
0(
#12916770
0-
#12917700
0.
0!
1(
#12959370
0(
#13001040
1.
b1011011 '
b1011011 1
b1110 &
b1110 0
1!
1(
#13042710
0(
#13084380
0.
0!
1(
#13126050
0(
#13167720
1.
b1001111 '
b1001111 1
b1111 &
b1111 0
1!
1(
#13209390
0(
#13251060
0.
0!
1(
#13292730
0(
#13333440
1+
1-
#13334400
1.
b101110 '
b101110 1
b0 &
b0 0
1!
0+
b0 %
b0 /
1*
1(
#13376070
0(
#13417740
0.
0!
0"
b111000 #
b111000 2
0*
1(
#13459410
0(
#13501080
1.
b101101 '
b101101 1
b1 &
b1 0
1!
1"
1(
#13542750
0(
#13584420
0.
0!
b111000 $
1(
#13626090
0(
#13667760
1.
b11000100 '
b11000100 1
b10 &
b10 0
1!
1(
#13709430
0(
#13750110
0-
#13751100
0.
0!
1(
#13792770
0(
#13834440
1.
b100100 '
b100100 1
b11 &
b11 0
1!
1(
#13876110
0(
#13917780
0.
0!
1(
#13959450
0(
#14001120
1.
b1101000 '
b1101000 1
b100 &
b100 0
1!
1(
#14042790
0(
#14084460
0.
0!
1(
#14126130
0(
#14166780
1+
1-
#14167800
1.
b1101011 '
b1101011 1
b101 &
b101 0
1!
0+
b1 %
b1 /
1*
1(
#14209470
0(
#14251140
0.
0!
0"
b101101 #
b101101 2
0*
1(
#14292810
0(
#14334480
1.
b101000 '
b101000 1
b110 &
b110 0
1!
1"
1(
#14376150
0(
#14417820
0.
0!
b101101 $
1(
#14459490
0(
#14501160
1.
b11001011 '
b11001011 1
b111 &
b111 0
1!
1(
#14542830
0(
#14583450
0-
#14584500
0.
0!
1(
#14626170
0(
#14667840
1.
b10000110 '
b10000110 1
b1000 &
b1000 0
1!
1(
#14709510
0(
#14751180
0.
0!
1(
#14792850
0(
#14834520
1.
b1100001 '
b1100001 1
b1001 &
b1001 0
1!
1(
#14876190
0(
#14917860
0.
0!
1(
#14959530
0(
#15000120
1+
1-
#15001200
1.
b11100100 '
b11100100 1
b1010 &
b1010 0
1!
0+
b10 %
b10 /
1*
1(
#15042870
0(
#15084540
0.
0!
0"
b11000100 #
b11000100 2
0*
1(
#15126210
0(
#15167880
1.
b111011 '
b111011 1
b1011 &
b1011 0
1!
1"
1(
#15209550
0(
#15251220
0.
0!
b11000100 $
1(
#15292890
0(
#15334560
1.
b10011110 '
b10011110 1
b1100 &
b1100 0
1!
1(
#15376230
0(
#15416790
0-
#15417900
0.
0!
1(
#15459570
0(
#15501240
1.
b10001001 '
b10001001 1
b1101 &
b1101 0
1!
1(
#15542910
0(
#15584580
0.
0!
1(
#15626250
0(
#15667920
1.
b111111 '
b111111 1
b1110 &
b1110 0
1!
1(
#15709590
0(
#15751260
0.
0!
1(
#15792930
0(
#15833460
1+
1-
#15834600
1.
b10110110 '
b10110110 1
b1111 &
b1111 0
1!
0+
b11 %
b11 /
1*
1(
#15876270
0(
#15917940
0.
0!
0"
b100100 #
b100100 2
0*
1(
#15959610
0(
#16001280
1.
b10011100 '
b10011100 1
b0 &
b0 0
1!
1"
1(
#16042950
0(
#16084620
0.
0!
b100100 $
1(
#16126290
0(
#16167960
1.
b10001111 '
b10001111 1
b1 &
b1 0
1!
1(
#16209630
0(
#16250130
0-
#16251300
0.
0!
1(
#16292970
0(
#16334640
1.
b1101001 '
b1101001 1
b10 &
b10 0
1!
1(
#16376310
0(
#16417980
0.
0!
1(
#16459650
0(
#16501320
1.
b11000010 '
b11000010 1
b11 &
b11 0
1!
1(
#16542990
0(
#16584660
0.
0!
1(
#16626330
0(
#16666800
1+
1-
#16668000
1.
b111100 '
b111100 1
b100 &
b100 0
1!
0+
b100 %
b100 /
1*
1(
#16709670
0(
#16751340
0.
0!
0"
b1101000 #
b1101000 2
0*
1(
#16793010
0(
#16834680
1.
b10101101 '
b10101101 1
b101 &
b101 0
1!
1"
1(
#16876350
0(
#16918020
0.
0!
b1101000 $
1(
#16959690
0(
#17001360
1.
b10100100 '
b10100100 1
b110 &
b110 0
1!
1(
#17043030
0(
#17083470
0-
#17084700
0.
0!
1(
#17126370
0(
#17168040
1.
b11111 '
b11111 1
b111 &
b111 0
1!
1(
#17209710
0(
#17251380
0.
0!
1(
#17293050
0(
#17334720
1.
b10010101 '
b10010101 1
b1000 &
b1000 0
1!
1(
#17376390
0(
#17418060
0.
0!
1(
#17459730
0(
#17500140
1+
1-
#17501400
1.
b10101100 '
b10101100 1
b1001 &
b1001 0
1!
0+
b101 %
b101 /
1*
1(
#17543070
0(
#17584740
0.
0!
0"
b10101101 #
b10101101 2
0*
1(
#17626410
0(
#17668080
1.
b1000011 '
b1000011 1
b1010 &
b1010 0
1!
1"
1(
#17709750
0(
#17751420
0.
0!
b10101101 $
1(
#17793090
0(
#17834760
1.
b1000111 '
b1000111 1
b1011 &
b1011 0
1!
1(
#17876430
0(
#17916810
0-
#17918100
0.
0!
1(
#17959770
0(
#18001440
1.
b1001110 '
b1001110 1
b1100 &
b1100 0
1!
1(
#18043110
0(
#18084780
0.
0!
1(
#18126450
0(
#18168120
1.
b11111101 '
b11111101 1
b1101 &
b1101 0
1!
1(
#18209790
0(
#18251460
0.
0!
1(
#18293130
0(
#18333480
1+
1-
#18334800
1.
b10011 '
b10011 1
b1110 &
b1110 0
1!
0+
b110 %
b110 /
1*
1(
#18376470
0(
#18418140
0.
0!
0"
b10100100 #
b10100100 2
0*
1(
#18459810
0(
#18501480
1.
b10111001 '
b10111001 1
b1111 &
b1111 0
1!
1"
1(
#18543150
0(
#18584820
0.
0!
b10100100 $
1(
#18626490
0(
#18668160
1.
b1010001 '
b1010001 1
b0 &
b0 0
1!
1(
#18709830
0(
#18750150
0-
#18751500
0.
0!
1(
#18793170
0(
#18834840
1.
b10111 '
b10111 1
b1 &
b1 0
1!
1(
#18876510
0(
#18918180
0.
0!
1(
#18959850
0(
#19001520
1.
b1011001 '
b1011001 1
b10 &
b10 0
1!
1(
#19043190
0(
#19084860
0.
0!
1(
#19126530
0(
#19166820
1+
1-
#19168200
1.
b101111 '
b101111 1
b11 &
b11 0
1!
0+
b111 %
b111 /
1*
1(
#19209870
0(
#19251540
0.
0!
0"
b11111 #
b11111 2
0*
1(
#19293210
0(
#19334880
1.
b10100010 '
b10100010 1
b100 &
b100 0
1!
1"
1(
#19376550
0(
#19418220
0.
0!
b11111 $
1(
#19459890
0(
#19501560
1.
b11111011 '
b11111011 1
b101 &
b101 0
1!
1(
#19543230
0(
#19583490
0-
#19584900
0.
0!
1(
#19626570
0(
#19668240
1.
b1100101 '
b1100101 1
b110 &
b110 0
1!
1(
#19709910
0(
#19751580
0.
0!
1(
#19793250
0(
#19834920
1.
b1110011 '
b1110011 1
b111 &
b111 0
1!
1(
#19876590
0(
#19918260
0.
0!
1(
#19959930
0(
#20000160
1+
1-
#20001600
1.
b10101101 '
b10101101 1
b1000 &
b1000 0
1!
0+
b1000 %
b1000 /
1*
1(
#20043270
0(
#20084940
0.
0!
0"
b10010101 #
b10010101 2
0*
1(
#20126610
0(
#20168280
1.
b10010100 '
b10010100 1
b1001 &
b1001 0
1!
1"
1(
#20209950
0(
#20251620
0.
0!
b10010101 $
1(
#20293290
0(
#20334960
1.
b1110110 '
b1110110 1
b1010 &
b1010 0
1!
1(
#20376630
0(
#20416830
0-
#20418300
0.
0!
1(
#20459970
0(
#20501640
1.
b1101101 '
b1101101 1
b1011 &
b1011 0
1!
1(
#20543310
0(
#20584980
0.
0!
1(
#20626650
0(
#20668320
1.
b110010 '
b110010 1
b1100 &
b1100 0
1!
1(
#20709990
0(
#20751660
0.
0!
1(
#20793330
0(
#20833500
1+
1-
#20835000
1.
b1011010 '
b1011010 1
b1101 &
b1101 0
1!
0+
b1001 %
b1001 /
1*
1(
#20876670
0(
#20918340
0.
0!
0"
b10010100 #
b10010100 2
0*
1(
#20960010
0(
#21001680
1.
b1101111 '
b1101111 1
b1110 &
b1110 0
1!
1"
1(
#21043350
0(
#21085020
0.
0!
b10010100 $
1(
#21126690
0(
#21168360
1.
b10111100 '
b10111100 1
b1111 &
b1111 0
1!
1(
#21210030
0(
#21250170
0-
#21251700
0.
0!
1(
#21293370
0(
#21335040
1.
b10100010 '
b10100010 1
b0 &
b0 0
1!
1(
#21376710
0(
#21418380
0.
0!
1(
#21460050
0(
#21501720
1.
b1101000 '
b1101000 1
b1 &
b1 0
1!
1(
#21543390
0(
#21585060
0.
0!
1(
#21626730
0(
#21666840
1+
1-
#21668400
1.
b10010101 '
b10010101 1
b10 &
b10 0
1!
0+
b1010 %
b1010 /
1*
1(
#21710070
0(
#21751740
0.
0!
0"
b1110110 #
b1110110 2
0*
1(
#21793410
0(
#21835080
1.
b11010101 '
b11010101 1
b11 &
b11 0
1!
1"
1(
#21876750
0(
#21918420
0.
0!
b1110110 $
1(
